{"id":1119,"name":"Benito González","nameLower":"benito gonzalez","results":[{"eventId":1720,"eventName":"VIANA Granfondo by KTM 2026","eventDate":"2026-03-15","eventYear":2026,"distance":"Granfondo","pos":331,"category":"Masters C","gender":"M","team":"Cc Bueu","country":"Spain","raceTime":"05:11:30","raceTimeSecs":18690.193,"gap":"01:47:03","gapSecs":6423.7,"dnf":false,"dns":false},{"eventId":1390,"eventName":"VIANA Granfondo 2025","eventDate":"2025-03-16","eventYear":2025,"distance":"Granfondo","pos":357,"category":"Masters C","gender":"M","team":"C.C.Bueu","country":"Spain","raceTime":"05:01:34","raceTimeSecs":18094.44,"gap":"01:41:43","gapSecs":6103.237,"dnf":false,"dns":false}],"canonicalTeam":"Cc Bueu"}