{"id":15938,"name":"Carlos Pereira","nameLower":"carlos pereira","results":[{"eventId":1880,"eventName":"Figueira Champions Classic 2026","eventDate":"2026-02-15","eventYear":2026,"distance":"HALF DAY","pos":166,"category":"Masters A","gender":"M","team":"Individual","country":"","raceTime":"02:26:45","raceTimeSecs":8805.727,"gap":"00:39:41","gapSecs":2381.87,"dnf":false,"dns":false},{"eventId":1439,"eventName":"Love Tiles Douro Granfondo 2025","eventDate":"2025-05-11","eventYear":2025,"distance":"Minifondo","pos":559,"category":"Masters A","gender":"M","team":"Individual","country":"","raceTime":"04:19:38","raceTimeSecs":15578.62,"gap":"02:11:02","gapSecs":7862.45,"dnf":false,"dns":false}]}