{"id":18220,"name":"Nuno Silva","nameLower":"nuno silva","results":[{"eventId":1656,"eventName":"Granfondo Torres Vedras 2025","eventDate":"2025-04-27","eventYear":2025,"distance":"Mediofondo","pos":334,"category":"Masters A","gender":"M","team":"Individual","country":"Portugal","raceTime":"03:51:56","raceTimeSecs":13916.563,"gap":"01:17:14","gapSecs":4634.366,"dnf":false,"dns":false},{"eventId":1390,"eventName":"VIANA Granfondo 2025","eventDate":"2025-03-16","eventYear":2025,"distance":"Minifondo","pos":315,"category":"Masters A","gender":"M","team":"Individual","country":"Portugal","raceTime":"03:02:27","raceTimeSecs":10947.663,"gap":"01:23:11","gapSecs":4991.763,"dnf":false,"dns":false}]}