{"id":1893,"name":"David Guerreiro","nameLower":"david guerreiro","teams":["ficalho dc clube dos trilhos"],"categories":{"2025":["MASTERS B"]},"results":[{"eventId":1780,"eventName":"GRANFONDO SERRA D’OSSA 2025","eventDate":"2025-10-05","eventYear":2025,"distance":"Mediofondo","pos":253,"category":"MASTERS B","gender":"M","team":"Ficalho Dc-Clube Dos Trilhos","country":"Portugal","raceTime":"03:26:39","raceTimeSecs":12399.64,"gap":"00:48:35","gapSecs":2915.173,"dnf":false,"dns":false}],"canonicalTeam":"Ficalho Dc-Clube Dos Trilhos"}