{"id":2219,"name":"Miguel Camilo","nameLower":"miguel camilo","teams":["marretas do oeste"],"categories":{"2025":["M ELITES"]},"results":[{"eventId":1759,"eventName":"Lousã Granfondo 2025","eventDate":"2025-09-14","eventYear":2025,"distance":"Granfondo","pos":58,"category":"M ELITES","gender":"M","team":"Marretas Do Oeste","country":"Portugal","raceTime":"04:19:24","raceTimeSecs":15564.64,"gap":"00:50:51","gapSecs":3051.287,"dnf":false,"dns":false},{"eventId":1681,"eventName":"Grandfondo Médio Tejo 2025","eventDate":"2025-05-25","eventYear":2025,"distance":"Granfondo","pos":69,"category":"M ELITES","gender":"M","team":"Individual","country":"Portugal","raceTime":"04:32:37","raceTimeSecs":16357.15,"gap":"00:48:21","gapSecs":2901.667,"dnf":false,"dns":false},{"eventId":1494,"eventName":"Algarve Granfondo 2025","eventDate":"2025-02-22","eventYear":2025,"distance":"Granfondo","pos":128,"category":"M ELITES","gender":"M","team":"Individual","country":"Portugal","raceTime":"04:16:25","raceTimeSecs":15385.563,"gap":"00:51:59","gapSecs":3119.666,"dnf":false,"dns":false}],"canonicalTeam":"Marretas Do Oeste"}