{"id":2741,"name":"Fabio Dias","nameLower":"fabio dias","results":[{"eventId":1780,"eventName":"GRANFONDO SERRA D’OSSA 2025","eventDate":"2025-10-05","eventYear":2025,"distance":"Minifondo","pos":157,"category":"Masters B","gender":"M","team":"Individual","country":"Portugal","raceTime":"02:21:49","raceTimeSecs":8509.013,"gap":"00:33:48","gapSecs":2028.823,"dnf":false,"dns":false},{"eventId":1759,"eventName":"Lousã Granfondo 2025","eventDate":"2025-09-14","eventYear":2025,"distance":"Minifondo","pos":6,"category":"Masters A","gender":"M","team":"Os Esbrutos","country":"Portugal","raceTime":"01:55:23","raceTimeSecs":6923.067,"gap":"00:03:53","gapSecs":233.497,"dnf":false,"dns":false},{"eventId":1505,"eventName":"SÃO MAMEDE GRANFONDO 2025","eventDate":"2025-06-08","eventYear":2025,"distance":"Minifondo","pos":16,"category":"Masters B","gender":"M","team":"Bjbikes \\ Municipio De Castelo De Vide","country":"Portugal","raceTime":"01:56:32","raceTimeSecs":6992.117,"gap":"00:14:34","gapSecs":874.764,"dnf":false,"dns":false},{"eventId":1656,"eventName":"Granfondo Torres Vedras 2025","eventDate":"2025-04-27","eventYear":2025,"distance":"Mediofondo","pos":23,"category":"Masters A","gender":"M","team":"Os Esbrutos","country":"Portugal","raceTime":"02:46:13","raceTimeSecs":9973.213,"gap":"00:11:31","gapSecs":691.016,"dnf":false,"dns":false}],"canonicalTeam":"Individual"}