{"id":3453,"name":"Joel Alves","nameLower":"joel alves","results":[{"eventId":1880,"eventName":"Figueira Champions Classic 2026","eventDate":"2026-02-15","eventYear":2026,"distance":"HALF DAY","pos":96,"category":"Masters A","gender":"M","team":"Indivídual","country":"","raceTime":"02:12:20","raceTimeSecs":7940.923,"gap":"00:25:17","gapSecs":1517.066,"dnf":false,"dns":false},{"eventId":1759,"eventName":"Lousã Granfondo 2025","eventDate":"2025-09-14","eventYear":2025,"distance":"Minifondo","pos":51,"category":"Masters A","gender":"M","team":"Individual","country":"Portugal","raceTime":"02:15:55","raceTimeSecs":8155.093,"gap":"00:24:25","gapSecs":1465.523,"dnf":false,"dns":false},{"eventId":1681,"eventName":"Grandfondo Médio Tejo 2025","eventDate":"2025-05-25","eventYear":2025,"distance":"Mediofondo","pos":353,"category":"Masters A","gender":"M","team":"Individual","country":"Portugal","raceTime":"04:36:16","raceTimeSecs":16576.153,"gap":"01:44:04","gapSecs":6244.636,"dnf":false,"dns":false},{"eventId":1401,"eventName":"EuroBEC Granfondo 2025","eventDate":"2025-04-06","eventYear":2025,"distance":"Mediofondo","pos":330,"category":"Masters A","gender":"M","team":"Individual","country":"Portugal","raceTime":"03:08:38","raceTimeSecs":11318.713,"gap":"00:39:57","gapSecs":2397.566,"dnf":false,"dns":false},{"eventId":1590,"eventName":"GRANFONDO COIMBRA REGION 2025","eventDate":"2025-03-02","eventYear":2025,"distance":"Mediofondo","pos":199,"category":"Masters A","gender":"M","team":"Individual","country":"Portugal","raceTime":"03:09:04","raceTimeSecs":11344.2,"gap":"00:27:29","gapSecs":1649.92,"dnf":false,"dns":false}]}