{"id":4318,"name":"João Jacinto","nameLower":"joao jacinto","results":[{"eventId":1831,"eventName":"Algarve Granfondo 2026","eventDate":"2026-02-21","eventYear":2026,"distance":"Mediofondo","pos":218,"category":"Elite","gender":"M","team":"Outsystems Olímpico De Oeiras","country":"Portugal","raceTime":"03:29:06","raceTimeSecs":12546.72,"gap":"00:50:24","gapSecs":3024.867,"dnf":false,"dns":false},{"eventId":1505,"eventName":"SÃO MAMEDE GRANFONDO 2025","eventDate":"2025-06-08","eventYear":2025,"distance":"Granfondo","pos":4,"category":"Elite","gender":"M","team":"Cdasj/Cyclin Team/Município Albufeira","country":"Portugal","raceTime":"03:48:51","raceTimeSecs":13731.213,"gap":"00:00:02","gapSecs":2.536,"dnf":false,"dns":false},{"eventId":1681,"eventName":"Grandfondo Médio Tejo 2025","eventDate":"2025-05-25","eventYear":2025,"distance":"Granfondo","pos":5,"category":"Elite","gender":"M","team":"Cdasj/Cyclin Team/Municipio Albufeira","country":"Portugal","raceTime":"03:44:40","raceTimeSecs":13480.343,"gap":"00:00:24","gapSecs":24.86,"dnf":false,"dns":false},{"eventId":1621,"eventName":"Aveiro Spring Classic 2025","eventDate":"2025-03-23","eventYear":2025,"distance":"Granfondo","pos":3,"category":"Elite","gender":"M","team":"Cdasj/Cyclin´Team/Município Albufeira","country":"Portugal","raceTime":"02:45:23","raceTimeSecs":9923.125,"gap":"00:00:00","gapSecs":0.025,"dnf":false,"dns":false},{"eventId":1494,"eventName":"Algarve Granfondo 2025","eventDate":"2025-02-22","eventYear":2025,"distance":"Granfondo","pos":3,"category":"Elite","gender":"M","team":"Cdasj/Cyclin´Team/Município Albufeira","country":"Portugal","raceTime":"03:28:48","raceTimeSecs":12528.158,"gap":"00:04:22","gapSecs":262.261,"dnf":false,"dns":false}],"canonicalTeam":"Outsystems Olímpico De Oeiras"}