{"id":4389,"name":"Miguel Graça","nameLower":"miguel graca","results":[{"eventId":1801,"eventName":"Granfondo de Portimão 2025 ","eventDate":"2025-11-02","eventYear":2025,"distance":"Minifondo","pos":157,"category":"Masters A","gender":"M","team":"Atlético Clube Fronteirense","country":"Portugal","raceTime":"02:28:37","raceTimeSecs":8917.503,"gap":"00:40:59","gapSecs":2459.08,"dnf":false,"dns":false},{"eventId":1505,"eventName":"SÃO MAMEDE GRANFONDO 2025","eventDate":"2025-06-08","eventYear":2025,"distance":"Mediofondo","pos":165,"category":"Masters A","gender":"M","team":"Atlético Clube Fronteirense","country":"Portugal","raceTime":"04:22:30","raceTimeSecs":15750.94,"gap":"01:50:25","gapSecs":6625.553,"dnf":false,"dns":false},{"eventId":1656,"eventName":"Granfondo Torres Vedras 2025","eventDate":"2025-04-27","eventYear":2025,"distance":"Minifondo","pos":196,"category":"Masters A","gender":"M","team":"Atlético Clube Fronteirense","country":"Portugal","raceTime":"03:01:14","raceTimeSecs":10874.747,"gap":"01:11:35","gapSecs":4295.627,"dnf":false,"dns":false},{"eventId":1401,"eventName":"EuroBEC Granfondo 2025","eventDate":"2025-04-06","eventYear":2025,"distance":"Mediofondo","pos":443,"category":"Masters A","gender":"M","team":"Atlético Clube Fronteirense","country":"Portugal","raceTime":"03:23:14","raceTimeSecs":12194.227,"gap":"00:54:33","gapSecs":3273.08,"dnf":false,"dns":false}],"canonicalTeam":"Atlético Clube Fronteirense"}