{"id":4586,"name":"João Branco","nameLower":"joao branco","teams":["painhas energy riders"],"categories":{"2026":["MASTERS B"]},"results":[{"eventId":1720,"eventName":"VIANA Granfondo by KTM 2026","eventDate":"2026-03-15","eventYear":2026,"distance":"Mediofondo","pos":611,"category":"MASTERS B","gender":"M","team":"Painhas Energy Riders","country":"Portugal","raceTime":"04:01:29","raceTimeSecs":14489.137,"gap":"01:26:12","gapSecs":5172.727,"dnf":false,"dns":false}],"canonicalTeam":"Painhas Energy Riders"}