{"id":5176,"name":"José Teixeira","nameLower":"jose teixeira","results":[{"eventId":1944,"eventName":"Aveiro Spring Classic 2026","eventDate":"2026-03-22","eventYear":2026,"distance":"Clássica","pos":107,"category":"Masters D","gender":"M","team":"Love Tiles","country":"Portugal","raceTime":"02:54:58","raceTimeSecs":10498.69,"gap":"00:15:17","gapSecs":917.023,"dnf":false,"dns":false},{"eventId":1720,"eventName":"VIANA Granfondo by KTM 2026","eventDate":"2026-03-15","eventYear":2026,"distance":"Granfondo","pos":329,"category":"Masters B","gender":"M","team":"The Dobstudio","country":"Portugal","raceTime":"05:09:16","raceTimeSecs":18556.493,"gap":"01:44:49","gapSecs":6289.1,"dnf":false,"dns":false},{"eventId":1720,"eventName":"VIANA Granfondo by KTM 2026","eventDate":"2026-03-15","eventYear":2026,"distance":"Mediofondo","pos":180,"category":"Masters A","gender":"M","team":"Individual","country":"Portugal","raceTime":"03:05:38","raceTimeSecs":11138.707,"gap":"00:30:22","gapSecs":1822.297,"dnf":false,"dns":false},{"eventId":1720,"eventName":"VIANA Granfondo by KTM 2026","eventDate":"2026-03-15","eventYear":2026,"distance":"Minifondo","pos":37,"category":"Masters D","gender":"M","team":"Love Tiles","country":"Portugal","raceTime":"01:43:04","raceTimeSecs":6184.813,"gap":"00:05:47","gapSecs":347.506,"dnf":false,"dns":false},{"eventId":1801,"eventName":"Granfondo de Portimão 2025 ","eventDate":"2025-11-02","eventYear":2025,"distance":"Minifondo","pos":23,"category":"Masters D","gender":"M","team":"Love Tiles","country":"Portugal","raceTime":"01:52:36","raceTimeSecs":6756.433,"gap":"00:04:58","gapSecs":298.01,"dnf":false,"dns":false},{"eventId":1553,"eventName":"MONÇÃO e MELGAÇO GF 2025","eventDate":"2025-09-21","eventYear":2025,"distance":"Mediofondo","pos":306,"category":"Elite","gender":"M","team":"Individual","country":"Portugal","raceTime":"03:54:29","raceTimeSecs":14069.053,"gap":"01:24:15","gapSecs":5055.873,"dnf":false,"dns":false},{"eventId":1553,"eventName":"MONÇÃO e MELGAÇO GF 2025","eventDate":"2025-09-21","eventYear":2025,"distance":"Minifondo","pos":24,"category":"Masters D","gender":"M","team":"Love Tiles","country":"Portugal","raceTime":"02:02:17","raceTimeSecs":7337.13,"gap":"00:08:13","gapSecs":493.267,"dnf":false,"dns":false},{"eventId":1759,"eventName":"Lousã Granfondo 2025","eventDate":"2025-09-14","eventYear":2025,"distance":"Minifondo","pos":15,"category":"Masters D","gender":"M","team":"Love Tiles","country":"Portugal","raceTime":"02:04:39","raceTimeSecs":7479.837,"gap":"00:13:10","gapSecs":790.267,"dnf":false,"dns":false},{"eventId":90002,"eventName":"Granfondo Agitágueda 2025","eventDate":"2025-07-27","eventYear":2025,"distance":"Minifondo","pos":17,"category":"Masters D","gender":"M","team":"","country":"","raceTime":"01:12:50","raceTimeSecs":4370,"gap":"","gapSecs":0,"dnf":false,"dns":false},{"eventId":1388,"eventName":"Bragança Granfondo 2025","eventDate":"2025-07-13","eventYear":2025,"distance":"Minifondo","pos":30,"category":"Masters D","gender":"M","team":"Love Tiles","country":"Portugal","raceTime":"01:34:02","raceTimeSecs":5642.183,"gap":"00:12:35","gapSecs":755.016,"dnf":false,"dns":false},{"eventId":1692,"eventName":"GRANFONDO TERRAS DE BASTO 2025","eventDate":"2025-06-15","eventYear":2025,"distance":"Minifondo","pos":30,"category":"Masters D","gender":"M","team":"Love Tiles","country":"Portugal","raceTime":"01:54:46","raceTimeSecs":6886.08,"gap":"00:17:23","gapSecs":1043.6,"dnf":false,"dns":false},{"eventId":1467,"eventName":"Gerês Granfondo 2025","eventDate":"2025-06-01","eventYear":2025,"distance":"Minifondo","pos":36,"category":"Masters D","gender":"M","team":"Love Tiles","country":"Portugal","raceTime":"02:27:21","raceTimeSecs":8841.477,"gap":"00:17:46","gapSecs":1066.024,"dnf":false,"dns":false},{"eventId":1681,"eventName":"Grandfondo Médio Tejo 2025","eventDate":"2025-05-25","eventYear":2025,"distance":"Minifondo","pos":28,"category":"Masters D","gender":"M","team":"Love Tiles","country":"Portugal","raceTime":"02:10:59","raceTimeSecs":7859.203,"gap":"00:10:40","gapSecs":640.266,"dnf":false,"dns":false},{"eventId":1439,"eventName":"Love Tiles Douro Granfondo 2025","eventDate":"2025-05-11","eventYear":2025,"distance":"Minifondo","pos":46,"category":"Masters D","gender":"M","team":"Love Tiles","country":"","raceTime":"02:20:21","raceTimeSecs":8421.187,"gap":"00:11:45","gapSecs":705.017,"dnf":false,"dns":false},{"eventId":1656,"eventName":"Granfondo Torres Vedras 2025","eventDate":"2025-04-27","eventYear":2025,"distance":"Mediofondo","pos":287,"category":"Masters B","gender":"M","team":"Individual","country":"Brazil","raceTime":"03:42:17","raceTimeSecs":13337.8,"gap":"01:07:35","gapSecs":4055.603,"dnf":false,"dns":false},{"eventId":1656,"eventName":"Granfondo Torres Vedras 2025","eventDate":"2025-04-27","eventYear":2025,"distance":"Minifondo","pos":25,"category":"Masters D","gender":"M","team":"Love Tiles","country":"Portugal","raceTime":"02:03:27","raceTimeSecs":7407.897,"gap":"00:13:48","gapSecs":828.777,"dnf":false,"dns":false},{"eventId":1401,"eventName":"EuroBEC Granfondo 2025","eventDate":"2025-04-06","eventYear":2025,"distance":"Minifondo","pos":30,"category":"Masters D","gender":"M","team":"Love Tiles","country":"Portugal","raceTime":"01:47:06","raceTimeSecs":6426.82,"gap":"00:04:25","gapSecs":265.51,"dnf":false,"dns":false},{"eventId":1621,"eventName":"Aveiro Spring Classic 2025","eventDate":"2025-03-23","eventYear":2025,"distance":"Granfondo","pos":131,"category":"Masters D","gender":"M","team":"Love Tiles","country":"Portugal","raceTime":"03:03:15","raceTimeSecs":10995.163,"gap":"00:17:52","gapSecs":1072.063,"dnf":false,"dns":false},{"eventId":1390,"eventName":"VIANA Granfondo 2025","eventDate":"2025-03-16","eventYear":2025,"distance":"Mediofondo","pos":5,"category":"Masters A","gender":"M","team":"Penacova  Ceg  Reconco","country":"Portugal","raceTime":"02:18:28","raceTimeSecs":8308.817,"gap":"00:01:17","gapSecs":77.754,"dnf":false,"dns":false},{"eventId":1390,"eventName":"VIANA Granfondo 2025","eventDate":"2025-03-16","eventYear":2025,"distance":"Minifondo","pos":37,"category":"Masters D","gender":"M","team":"Love Tiles","country":"Portugal","raceTime":"01:45:38","raceTimeSecs":6338.5,"gap":"00:06:22","gapSecs":382.6,"dnf":false,"dns":false},{"eventId":1590,"eventName":"GRANFONDO COIMBRA REGION 2025","eventDate":"2025-03-02","eventYear":2025,"distance":"Mediofondo","pos":121,"category":"Masters D","gender":"M","team":"Love Tiles","country":"Portugal","raceTime":"03:00:47","raceTimeSecs":10847.58,"gap":"00:19:13","gapSecs":1153.3,"dnf":false,"dns":false},{"eventId":90001,"eventName":"Figueira Champions Day 2025","eventDate":"2025-02-15","eventYear":2025,"distance":"Mediofondo","pos":2,"category":"Masters A","gender":"M","team":"Penacova CEG Reconco","country":"PT","raceTime":"01:59:53","raceTimeSecs":7193,"gap":"","gapSecs":0,"dnf":false,"dns":false}],"canonicalTeam":"Love Tiles"}