{"id":5308,"name":"Guilherme Carvalho","nameLower":"guilherme carvalho","results":[{"eventId":1780,"eventName":"GRANFONDO SERRA D’OSSA 2025","eventDate":"2025-10-05","eventYear":2025,"distance":"Minifondo","pos":130,"category":"Masters B","gender":"M","team":"Adbn Bike & Nutrition Shop","country":"Portugal","raceTime":"02:16:42","raceTimeSecs":8202,"gap":"00:28:41","gapSecs":1721.81,"dnf":false,"dns":false},{"eventId":1681,"eventName":"Grandfondo Médio Tejo 2025","eventDate":"2025-05-25","eventYear":2025,"distance":"Mediofondo","pos":214,"category":"Masters B","gender":"M","team":"Bike Nutricion Shop","country":"Portugal","raceTime":"03:49:18","raceTimeSecs":13758.6,"gap":"00:57:07","gapSecs":3427.083,"dnf":false,"dns":false},{"eventId":1401,"eventName":"EuroBEC Granfondo 2025","eventDate":"2025-04-06","eventYear":2025,"distance":"Granfondo","pos":137,"category":"Masters B","gender":"M","team":"Bike & Nutrition Shop","country":"Portugal","raceTime":"04:10:16","raceTimeSecs":15016.777,"gap":"00:32:06","gapSecs":1926.784,"dnf":false,"dns":false},{"eventId":1590,"eventName":"GRANFONDO COIMBRA REGION 2025","eventDate":"2025-03-02","eventYear":2025,"distance":"Granfondo","pos":266,"category":"Masters B","gender":"M","team":"Bike & Nutrition Shop","country":"Portugal","raceTime":"04:29:26","raceTimeSecs":16166.303,"gap":"00:44:21","gapSecs":2661.36,"dnf":false,"dns":false},{"eventId":1494,"eventName":"Algarve Granfondo 2025","eventDate":"2025-02-22","eventYear":2025,"distance":"Mediofondo","pos":177,"category":"Masters B","gender":"M","team":"Adbn Bike & Nutrition Shop","country":"Portugal","raceTime":"02:54:12","raceTimeSecs":10452.45,"gap":"00:37:02","gapSecs":2222.71,"dnf":false,"dns":false}],"canonicalTeam":"Adbn Bike & Nutrition Shop"}