{"id":6428,"name":"Alberto Domínguez","nameLower":"alberto dominguez","teams":["jovenes ciclistas mirobrigenses"],"categories":{"2025":["MASTERS A"]},"results":[{"eventId":1362,"eventName":"Granfondo Serra da Estrela 2025","eventDate":"2025-06-29","eventYear":2025,"distance":"Granfondo","pos":24,"category":"MASTERS A","gender":"M","team":"Jovenes Ciclistas Mirobrigenses","country":"Spain","raceTime":"05:16:08","raceTimeSecs":18968.343,"gap":"00:53:35","gapSecs":3215.393,"dnf":false,"dns":false}],"canonicalTeam":"Jovenes Ciclistas Mirobrigenses"}