{"id":6999,"name":"Antsnio Pereira","nameLower":"antsnio pereira","teams":["gdbp"],"categories":{"2025":["MASTERS E"]},"results":[{"eventId":1467,"eventName":"Gerês Granfondo 2025","eventDate":"2025-06-01","eventYear":2025,"distance":"Mediofondo","pos":369,"category":"MASTERS E","gender":"M","team":"Gdbp","country":"Portugal","raceTime":"05:57:19","raceTimeSecs":21439.903,"gap":"02:57:00","gapSecs":10620.383,"dnf":false,"dns":false},{"eventId":1439,"eventName":"Love Tiles Douro Granfondo 2025","eventDate":"2025-05-11","eventYear":2025,"distance":"Mediofondo","pos":860,"category":"MASTERS E","gender":"M","team":"Gdbp","country":"","raceTime":"05:25:25","raceTimeSecs":19525.757,"gap":"02:34:58","gapSecs":9298.767,"dnf":false,"dns":false},{"eventId":1401,"eventName":"EuroBEC Granfondo 2025","eventDate":"2025-04-06","eventYear":2025,"distance":"Mediofondo","pos":673,"category":"MASTERS E","gender":"M","team":"Gdbp","country":"Portugal","raceTime":"04:09:14","raceTimeSecs":14954.53,"gap":"01:40:33","gapSecs":6033.383,"dnf":false,"dns":false}],"canonicalTeam":"Gdbp"}