{"id":7343,"name":"Diogo Franco","nameLower":"diogo franco","results":[{"eventId":1362,"eventName":"Granfondo Serra da Estrela 2025","eventDate":"2025-06-29","eventYear":2025,"distance":"Granfondo","pos":65,"category":"Elite","gender":"M","team":"Ipoc/Apoc/Bikeinstant","country":"Portugal","raceTime":"05:47:17","raceTimeSecs":20837.597,"gap":"01:24:44","gapSecs":5084.647,"dnf":false,"dns":false},{"eventId":1681,"eventName":"Grandfondo Médio Tejo 2025","eventDate":"2025-05-25","eventYear":2025,"distance":"Granfondo","pos":12,"category":"Elite","gender":"M","team":"Ipoc/Apoc/Bikeinstant","country":"Portugal","raceTime":"03:46:49","raceTimeSecs":13609.847,"gap":"00:02:34","gapSecs":154.364,"dnf":false,"dns":false}],"canonicalTeam":"Ipoc / Apoc / Bikeinstant"}