{"id":8164,"name":"Eurico Calvelhe","nameLower":"eurico calvelhe","results":[{"eventId":1692,"eventName":"GRANFONDO TERRAS DE BASTO 2025","eventDate":"2025-06-15","eventYear":2025,"distance":"Minifondo","pos":240,"category":"Masters D","gender":"M","team":"Rubis Gas","country":"Portugal","raceTime":"03:48:31","raceTimeSecs":13711.287,"gap":"02:11:08","gapSecs":7868.807,"dnf":false,"dns":false},{"eventId":1681,"eventName":"Grandfondo Médio Tejo 2025","eventDate":"2025-05-25","eventYear":2025,"distance":"Minifondo","pos":181,"category":"Masters D","gender":"M","team":"Rubis Gás","country":"Portugal","raceTime":"03:01:48","raceTimeSecs":10908.777,"gap":"01:01:29","gapSecs":3689.84,"dnf":false,"dns":false}],"canonicalTeam":"Rubis Gas"}