{"id":839,"name":"António Henriques","nameLower":"antonio henriques","results":[{"eventId":1780,"eventName":"GRANFONDO SERRA D’OSSA 2025","eventDate":"2025-10-05","eventYear":2025,"distance":"Granfondo","pos":52,"category":"Masters C","gender":"M","team":"Duros Do Pedal","country":"Portugal","raceTime":"03:41:30","raceTimeSecs":13290.667,"gap":"00:25:50","gapSecs":1550.54,"dnf":false,"dns":false},{"eventId":1780,"eventName":"GRANFONDO SERRA D’OSSA 2025","eventDate":"2025-10-05","eventYear":2025,"distance":"Minifondo","pos":238,"category":"Masters D","gender":"M","team":"Rc Team","country":"Portugal","raceTime":"02:40:46","raceTimeSecs":9646.05,"gap":"00:52:45","gapSecs":3165.86,"dnf":false,"dns":false}],"canonicalTeam":"Duros Do Pedal"}