{"id":8455,"name":"Rui Sousa","nameLower":"rui sousa","results":[{"eventId":1467,"eventName":"Gerês Granfondo 2025","eventDate":"2025-06-01","eventYear":2025,"distance":"Minifondo","pos":188,"category":"Masters C","gender":"M","team":"Grupo Beleza Cesar Racing","country":"Portugal","raceTime":"03:21:15","raceTimeSecs":12075.28,"gap":"01:11:39","gapSecs":4299.827,"dnf":false,"dns":false},{"eventId":1439,"eventName":"Love Tiles Douro Granfondo 2025","eventDate":"2025-05-11","eventYear":2025,"distance":"Minifondo","pos":296,"category":"Masters C","gender":"M","team":"Cesar Racing","country":"","raceTime":"03:11:27","raceTimeSecs":11487.517,"gap":"01:02:51","gapSecs":3771.347,"dnf":false,"dns":false},{"eventId":1390,"eventName":"VIANA Granfondo 2025","eventDate":"2025-03-16","eventYear":2025,"distance":"Minifondo","pos":183,"category":"Masters B","gender":"M","team":"Individual","country":"Portugal","raceTime":"02:16:37","raceTimeSecs":8197.82,"gap":"00:37:21","gapSecs":2241.92,"dnf":false,"dns":false}],"canonicalTeam":"Grupo Beleza Cesar Racing"}