{"id":8828,"name":"Telma Roque","nameLower":"telma roque","results":[{"eventId":1759,"eventName":"Lousã Granfondo 2025","eventDate":"2025-09-14","eventYear":2025,"distance":"Minifondo","pos":260,"category":"Elite F","gender":"F","team":"Juventude Ouriense","country":"Portugal","raceTime":"03:32:00","raceTimeSecs":12720.14,"gap":"01:40:30","gapSecs":6030.57,"dnf":false,"dns":false},{"eventId":1681,"eventName":"Grandfondo Médio Tejo 2025","eventDate":"2025-05-25","eventYear":2025,"distance":"Minifondo","pos":297,"category":"Elite F","gender":"F","team":"Juventude Ouriense","country":"Portugal","raceTime":"04:02:45","raceTimeSecs":14565.607,"gap":"02:02:26","gapSecs":7346.67,"dnf":false,"dns":false}],"canonicalTeam":"Juventude Ouriense"}