{"id":9521,"name":"Pedro Oliveira","nameLower":"pedro oliveira","results":[{"eventId":1720,"eventName":"VIANA Granfondo by KTM 2026","eventDate":"2026-03-15","eventYear":2026,"distance":"Granfondo","pos":389,"category":"Masters C","gender":"M","team":"Galu Fritu","country":"Portugal","raceTime":"05:40:49","raceTimeSecs":20449.243,"gap":"02:16:22","gapSecs":8182.75,"dnf":false,"dns":false},{"eventId":1720,"eventName":"VIANA Granfondo by KTM 2026","eventDate":"2026-03-15","eventYear":2026,"distance":"Minifondo","pos":223,"category":"Elite","gender":"M","team":"Elite Place","country":"Portugal","raceTime":"02:17:07","raceTimeSecs":8227.12,"gap":"00:39:49","gapSecs":2389.813,"dnf":false,"dns":false},{"eventId":1759,"eventName":"Lousã Granfondo 2025","eventDate":"2025-09-14","eventYear":2025,"distance":"Minifondo","pos":70,"category":"Masters C","gender":"M","team":"Secai/Gaiabike/Geoinerte/Forestcity","country":"Portugal","raceTime":"02:22:29","raceTimeSecs":8549.09,"gap":"00:30:59","gapSecs":1859.52,"dnf":false,"dns":false},{"eventId":90002,"eventName":"Granfondo Agitágueda 2025","eventDate":"2025-07-27","eventYear":2025,"distance":"Mediofondo","pos":169,"category":"Elite","gender":"M","team":"","country":"","raceTime":"02:58:00","raceTimeSecs":10680,"gap":"","gapSecs":0,"dnf":false,"dns":false},{"eventId":1692,"eventName":"GRANFONDO TERRAS DE BASTO 2025","eventDate":"2025-06-15","eventYear":2025,"distance":"Minifondo","pos":141,"category":"Elite","gender":"M","team":"Elite Place","country":"Portugal","raceTime":"02:35:39","raceTimeSecs":9339.14,"gap":"00:58:16","gapSecs":3496.66,"dnf":false,"dns":false},{"eventId":1467,"eventName":"Gerês Granfondo 2025","eventDate":"2025-06-01","eventYear":2025,"distance":"Mediofondo","pos":279,"category":"Masters B","gender":"M","team":"Pitosga-Acvâncora","country":"Portugal","raceTime":"04:42:49","raceTimeSecs":16969.1,"gap":"01:42:29","gapSecs":6149.58,"dnf":false,"dns":false},{"eventId":1439,"eventName":"Love Tiles Douro Granfondo 2025","eventDate":"2025-05-11","eventYear":2025,"distance":"Mediofondo","pos":351,"category":"Masters A","gender":"M","team":"Individual","country":"","raceTime":"03:43:10","raceTimeSecs":13390.563,"gap":"00:52:43","gapSecs":3163.573,"dnf":false,"dns":false},{"eventId":1401,"eventName":"EuroBEC Granfondo 2025","eventDate":"2025-04-06","eventYear":2025,"distance":"Minifondo","pos":84,"category":"Masters D","gender":"M","team":"Academia Joaquim Agostinho","country":"Portugal","raceTime":"01:58:43","raceTimeSecs":7123.343,"gap":"00:16:02","gapSecs":962.033,"dnf":false,"dns":false},{"eventId":1621,"eventName":"Aveiro Spring Classic 2025","eventDate":"2025-03-23","eventYear":2025,"distance":"Granfondo","pos":326,"category":"Masters D","gender":"M","team":"Sport União Torreense/Cyr","country":"Portugal","raceTime":"03:18:58","raceTimeSecs":11938.453,"gap":"00:33:35","gapSecs":2015.353,"dnf":false,"dns":false},{"eventId":1390,"eventName":"VIANA Granfondo 2025","eventDate":"2025-03-16","eventYear":2025,"distance":"Mediofondo","pos":267,"category":"Masters A","gender":"M","team":"Individual","country":"Portugal","raceTime":"03:02:44","raceTimeSecs":10964.917,"gap":"00:45:33","gapSecs":2733.854,"dnf":false,"dns":false},{"eventId":1590,"eventName":"GRANFONDO COIMBRA REGION 2025","eventDate":"2025-03-02","eventYear":2025,"distance":"Mediofondo","pos":291,"category":"Masters D","gender":"M","team":"Sport União Torreense/Cyr","country":"Portugal","raceTime":"03:21:37","raceTimeSecs":12097.633,"gap":"00:40:03","gapSecs":2403.353,"dnf":false,"dns":false},{"eventId":90001,"eventName":"Figueira Champions Day 2025","eventDate":"2025-02-15","eventYear":2025,"distance":"Mediofondo","pos":173,"category":"Masters D","gender":"M","team":"Academia Joaquim Agostinho","country":"PT","raceTime":"02:32:55","raceTimeSecs":9175,"gap":"","gapSecs":0,"dnf":false,"dns":false}],"canonicalTeam":"Galu Fritu"}