{"name": "Alberto Veloso", "nameLower": "alberto veloso", "results": [{"eventId": 1388, "eventName": "Bragança Granfondo 2025", "eventDate": "2025-07-13", "eventYear": 2025, "distance": "Mediofondo", "pos": 292, "category": "MASTERS C", "gender": "M", "team": "Clube De Ciclismo De Vila Flor", "country": "Portugal", "raceTime": "04:05:12", "raceTimeSecs": 14712.333, "gap": "01:38:41", "gapSecs": 5921.833, "dnf": false, "dns": false}, {"eventId": 1467, "eventName": "Gerês Granfondo 2025", "eventDate": "2025-06-01", "eventYear": 2025, "distance": "Mediofondo", "pos": 220, "category": "MASTERS C", "gender": "M", "team": "Individual", "country": "Luxembourg", "raceTime": "04:17:53", "raceTimeSecs": 15473.827, "gap": "01:17:34", "gapSecs": 4654.307, "dnf": false, "dns": false}, {"eventId": 1439, "eventName": "Love Tiles Douro Granfondo 2025", "eventDate": "2025-05-11", "eventYear": 2025, "distance": "Mediofondo", "pos": 472, "category": "MASTERS C", "gender": "M", "team": "Individual", "country": "", "raceTime": "03:58:55", "raceTimeSecs": 14335.837, "gap": "01:08:28", "gapSecs": 4108.847, "dnf": false, "dns": false}], "canonicalTeam": "Individual"}