{"name":"Alexandre Rodrigues","nameLower":"alexandre rodrigues","slug":"alexandre-rodrigues","results":[{"eventId":1362,"eventName":"Granfondo Serra da Estrela 2025","eventDate":"2025-06-29","eventYear":2025,"distance":"Granfondo","pos":135,"category":"M ELITES","gender":"M","team":"Individual","country":"Portugal","raceTime":"06:28:38","raceTimeSecs":23318.95,"gap":"02:06:06","gapSecs":7566,"dnf":false,"dns":false},{"eventId":1681,"eventName":"Grandfondo Médio Tejo 2025","eventDate":"2025-05-25","eventYear":2025,"distance":"Mediofondo","pos":388,"category":"MASTERS C","gender":"M","team":"Individual","country":"Portugal","raceTime":"04:44:54","raceTimeSecs":17094.163,"gap":"01:52:42","gapSecs":6762.646,"dnf":false,"dns":false},{"eventId":1656,"eventName":"Granfondo Torres Vedras 2025","eventDate":"2025-04-27","eventYear":2025,"distance":"Granfondo","pos":80,"category":"M ELITES","gender":"M","team":"Individual","country":"Portugal","raceTime":"04:47:05","raceTimeSecs":17225.887,"gap":"01:00:03","gapSecs":3603.33,"dnf":false,"dns":false}]}