{"name": "Ángel Gallardo", "nameLower": "angel gallardo", "results": [{"eventId": 1505, "eventName": "SÃO MAMEDE GRANFONDO 2025", "eventDate": "2025-06-08", "eventYear": 2025, "distance": "Minifondo", "pos": 86, "category": "MASTER 50", "gender": "M", "team": "Club Maratón Badajoz", "country": "Spain", "raceTime": "02:35:37", "raceTimeSecs": 9337.137, "gap": "00:53:39", "gapSecs": 3219.784, "dnf": false, "dns": false}, {"eventId": 1401, "eventName": "EuroBEC Granfondo 2025", "eventDate": "2025-04-06", "eventYear": 2025, "distance": "Mediofondo", "pos": 233, "category": "MASTERS C", "gender": "M", "team": "Club Maratón Badajoz", "country": "Spain", "raceTime": "02:58:20", "raceTimeSecs": 10700.947, "gap": "00:29:39", "gapSecs": 1779.8, "dnf": false, "dns": false}], "canonicalTeam": "Club Maratón Badajoz"}