{"name":"Bernardo Santos","nameLower":"bernardo santos","slug":"bernardo-santos-lb-squad","results":[{"eventId":1720,"eventName":"VIANA Granfondo by KTM 2026","eventDate":"2026-03-15","eventYear":2026,"distance":"Granfondo","pos":408,"category":"Elite","gender":"M","team":"Individual","country":"Portugal","raceTime":"06:01:16","raceTimeSecs":21676.057,"gap":"02:36:49","gapSecs":9409.564,"dnf":false,"dns":false},{"eventId":1362,"eventName":"Granfondo Serra da Estrela 2025","eventDate":"2025-06-29","eventYear":2025,"distance":"Mediofondo","pos":430,"category":"Elite","gender":"M","team":"Lb Squad","country":"Portugal","raceTime":"05:40:10","raceTimeSecs":20410.237,"gap":"02:51:06","gapSecs":10266.137,"dnf":false,"dns":false}],"canonicalTeam":"Individual"}