{"name":"Bruno Gonçalves","nameLower":"bruno goncalves","slug":"bruno-goncalves","results":[{"eventId":1720,"eventName":"VIANA Granfondo by KTM 2026","eventDate":"2026-03-15","eventYear":2026,"distance":"Mediofondo","pos":426,"category":"MASTERS A","gender":"M","team":"Individual","country":"Portugal","raceTime":"03:38:01","raceTimeSecs":13081.017,"gap":"01:02:44","gapSecs":3764.607,"dnf":false,"dns":false},{"eventId":1612,"eventName":"TAVIRA GRANFONDO 2025","eventDate":"2025-09-28","eventYear":2025,"distance":"Mediofondo","pos":58,"category":"MASTERS A","gender":"M","team":"Individual","country":"Portugal","raceTime":"03:51:34","raceTimeSecs":13894.863,"gap":"01:01:49","gapSecs":3709.1,"dnf":false,"dns":false},{"eventId":90002,"eventName":"Granfondo Agitágueda 2025","eventDate":"2025-07-27","eventYear":2025,"distance":"Mediofondo","pos":308,"category":"M Masters A","gender":"M","team":"","country":"","raceTime":"03:43:11","raceTimeSecs":13391,"gap":"","gapSecs":0,"dnf":false,"dns":false},{"eventId":1692,"eventName":"GRANFONDO TERRAS DE BASTO 2025","eventDate":"2025-06-15","eventYear":2025,"distance":"Mediofondo","pos":168,"category":"MASTERS A","gender":"M","team":"Individual","country":"Portugal","raceTime":"04:20:18","raceTimeSecs":15618.793,"gap":"01:21:33","gapSecs":4893.426,"dnf":false,"dns":false},{"eventId":1494,"eventName":"Algarve Granfondo 2025","eventDate":"2025-02-22","eventYear":2025,"distance":"Mediofondo","pos":309,"category":"MASTERS A","gender":"M","team":"Individual","country":"Portugal","raceTime":"03:14:12","raceTimeSecs":11652.627,"gap":"00:57:02","gapSecs":3422.887,"dnf":false,"dns":false}]}