{"name": "Daniela Boas", "nameLower": "daniela boas", "results": [{"eventId": 1388, "eventName": "Bragança Granfondo 2025", "eventDate": "2025-07-13", "eventYear": 2025, "distance": "Minifondo", "pos": 94, "category": "MASTERS A FEM", "gender": "F", "team": "Brinox Cycling Team", "country": "Portugal", "raceTime": "01:57:37", "raceTimeSecs": 7057.457, "gap": "00:36:10", "gapSecs": 2170.29, "dnf": false, "dns": false}, {"eventId": 1467, "eventName": "Gerês Granfondo 2025", "eventDate": "2025-06-01", "eventYear": 2025, "distance": "Minifondo", "pos": 92, "category": "MASTERS A FEM", "gender": "F", "team": "Brinox Cycling Team", "country": "Portugal", "raceTime": "02:45:45", "raceTimeSecs": 9945.743, "gap": "00:36:10", "gapSecs": 2170.29, "dnf": false, "dns": false}, {"eventId": 1439, "eventName": "Love Tiles Douro Granfondo 2025", "eventDate": "2025-05-11", "eventYear": 2025, "distance": "Minifondo", "pos": 138, "category": "MASTERS A FEM", "gender": "F", "team": "Brinox Cycling Team", "country": "", "raceTime": "02:43:19", "raceTimeSecs": 9799.72, "gap": "00:34:43", "gapSecs": 2083.55, "dnf": false, "dns": false}, {"eventId": 1656, "eventName": "Granfondo Torres Vedras 2025", "eventDate": "2025-04-27", "eventYear": 2025, "distance": "Minifondo", "pos": 72, "category": "F MASTERS A", "gender": "F", "team": "Brinox Cycling Team", "country": "Portugal", "raceTime": "02:21:05", "raceTimeSecs": 8465.673, "gap": "00:31:26", "gapSecs": 1886.553, "dnf": false, "dns": false}, {"eventId": 1401, "eventName": "EuroBEC Granfondo 2025", "eventDate": "2025-04-06", "eventYear": 2025, "distance": "Minifondo", "pos": 96, "category": "MASTERS A FEM", "gender": "F", "team": "Brinox Cycling Team", "country": "Portugal", "raceTime": "02:01:10", "raceTimeSecs": 7270.347, "gap": "00:18:29", "gapSecs": 1109.037, "dnf": false, "dns": false}, {"eventId": 1390, "eventName": "VIANA Granfondo 2025", "eventDate": "2025-03-16", "eventYear": 2025, "distance": "Minifondo", "pos": 99, "category": "MASTERS A FEM", "gender": "F", "team": "Brinox Cycling Team", "country": "Portugal", "raceTime": "02:00:15", "raceTimeSecs": 7215.533, "gap": "00:20:59", "gapSecs": 1259.633, "dnf": false, "dns": false}, {"eventId": 1590, "eventName": "GRANFONDO COIMBRA REGION 2025", "eventDate": "2025-03-02", "eventYear": 2025, "distance": "Mediofondo", "pos": 350, "category": "F 19-34", "gender": "F", "team": "Brinox Cycling Team", "country": "Portugal", "raceTime": "03:31:48", "raceTimeSecs": 12708.91, "gap": "00:50:14", "gapSecs": 3014.63, "dnf": false, "dns": false}, {"eventId": 1592, "eventName": "TIME TRIAL GRANFONDO COIMBRA REGION 2025", "eventDate": "2025-03-01", "eventYear": 2025, "distance": "Time Trial", "pos": 201, "category": "F 19-34", "gender": "F", "team": "Brinox Cycling Team", "country": "Portugal", "raceTime": "00:37:04", "raceTimeSecs": 2224.77, "gap": "00:10:47", "gapSecs": 647.403, "dnf": false, "dns": false}], "canonicalTeam": "Brinox Cycling Team"}