{"name":"Eduardo Soares","nameLower":"eduardo soares","slug":"eduardo-soares","results":[{"eventId":1467,"eventName":"Gerês Granfondo 2025","eventDate":"2025-06-01","eventYear":2025,"distance":"Mediofondo","pos":238,"category":"Masters C","gender":"M","team":"Individual","country":"Brazil","raceTime":"04:24:27","raceTimeSecs":15867.087,"gap":"01:24:07","gapSecs":5047.567,"dnf":false,"dns":false},{"eventId":1439,"eventName":"Love Tiles Douro Granfondo 2025","eventDate":"2025-05-11","eventYear":2025,"distance":"Mediofondo","pos":584,"category":"Masters C","gender":"M","team":"Individual","country":"","raceTime":"04:15:01","raceTimeSecs":15301.36,"gap":"01:24:34","gapSecs":5074.37,"dnf":false,"dns":false}],"canonicalTeam":"Individual"}