{"name":"Isidro Vasco","nameLower":"isidro vasco","slug":"isidro-vasco-rbwcyclingteam","results":[{"eventId":1656,"eventName":"Granfondo Torres Vedras 2025","eventDate":"2025-04-27","eventYear":2025,"distance":"Mediofondo","pos":342,"category":"MASTERS B","gender":"M","team":"Rbwcyclingteam","country":"Portugal","raceTime":"03:53:53","raceTimeSecs":14033.823,"gap":"01:19:11","gapSecs":4751.626,"dnf":false,"dns":false},{"eventId":1401,"eventName":"EuroBEC Granfondo 2025","eventDate":"2025-04-06","eventYear":2025,"distance":"Mediofondo","pos":427,"category":"MASTERS B","gender":"M","team":"Rbwcyclingteam","country":"Portugal","raceTime":"03:21:24","raceTimeSecs":12084.473,"gap":"00:52:43","gapSecs":3163.326,"dnf":false,"dns":false}],"canonicalTeam":"Rbwcyclingteam"}