{"name": "Joao Martins", "nameLower": "joao martins", "results": [{"eventId": 1720, "eventName": "VIANA Granfondo by KTM 2026", "eventDate": "2026-03-15", "eventYear": 2026, "distance": "Minifondo", "pos": 110, "category": "MASTERS B", "gender": "M", "team": "Individual", "country": "Portugal", "raceTime": "01:59:02", "raceTimeSecs": 7142.083, "gap": "00:21:44", "gapSecs": 1304.776, "dnf": false, "dns": false}, {"eventId": 1720, "eventName": "VIANA Granfondo by KTM 2026", "eventDate": "2026-03-15", "eventYear": 2026, "distance": "Minifondo", "pos": 163, "category": "MASTERS A", "gender": "M", "team": "Individual", "country": "Portugal", "raceTime": "02:06:13", "raceTimeSecs": 7573.107, "gap": "00:28:55", "gapSecs": 1735.8, "dnf": false, "dns": false}, {"eventId": 1831, "eventName": "Algarve Granfondo 2026", "eventDate": "2026-02-21", "eventYear": 2026, "distance": "Mediofondo", "pos": 2, "category": "MASTERS A", "gender": "M", "team": "Mirachoro Hotels - Centro De Ciclismo De Portimão", "country": "Portugal", "raceTime": "02:38:42", "raceTimeSecs": 9522.107, "gap": "00:00:00", "gapSecs": 0.254, "dnf": false, "dns": false}, {"eventId": 1801, "eventName": "Granfondo de Portimão 2025 ", "eventDate": "2025-11-02", "eventYear": 2025, "distance": "Granfondo", "pos": 14, "category": "MASTERS C", "gender": "M", "team": "Garra - Onebike", "country": "Portugal", "raceTime": "03:52:27", "raceTimeSecs": 13947.893, "gap": "00:15:15", "gapSecs": 915.77, "dnf": false, "dns": false}, {"eventId": 1801, "eventName": "Granfondo de Portimão 2025 ", "eventDate": "2025-11-02", "eventYear": 2025, "distance": "Mediofondo", "pos": 5, "category": "MASTERS A", "gender": "M", "team": "Mirachoro Hotels - Centro De Ciclismo De Portimão - Churrasqueira Guerreiro", "country": "Portugal", "raceTime": "02:42:59", "raceTimeSecs": 9779.2, "gap": "00:00:02", "gapSecs": 2.17, "dnf": false, "dns": false}, {"eventId": 1780, "eventName": "GRANFONDO SERRA D’OSSA 2025", "eventDate": "2025-10-05", "eventYear": 2025, "distance": "Mediofondo", "pos": 75, "category": "MASTERS A", "gender": "M", "team": "Lusitano De Évora", "country": "Portugal", "raceTime": "02:52:48", "raceTimeSecs": 10368.573, "gap": "00:14:44", "gapSecs": 884.106, "dnf": false, "dns": false}, {"eventId": 1780, "eventName": "GRANFONDO SERRA D’OSSA 2025", "eventDate": "2025-10-05", "eventYear": 2025, "distance": "Minifondo", "pos": 264, "category": "MASTERS B", "gender": "M", "team": "Team Rebeldex", "country": "Portugal", "raceTime": "02:44:12", "raceTimeSecs": 9852.307, "gap": "00:56:12", "gapSecs": 3372.117, "dnf": false, "dns": false}, {"eventId": 1612, "eventName": "TAVIRA GRANFONDO 2025", "eventDate": "2025-09-28", "eventYear": 2025, "distance": "Granfondo", "pos": 24, "category": "MASTERS C", "gender": "M", "team": "Adect / Cmsantos.Pt", "country": "Portugal", "raceTime": "03:51:07", "raceTimeSecs": 13867.363, "gap": "00:26:48", "gapSecs": 1608.04, "dnf": false, "dns": false}, {"eventId": 1612, "eventName": "TAVIRA GRANFONDO 2025", "eventDate": "2025-09-28", "eventYear": 2025, "distance": "Mediofondo", "pos": 2, "category": "MASTERS A", "gender": "M", "team": "Mirachoro Hotels - Centro De Ciclismo De Portimão - Churrasqueira  Guerreiro", "country": "Portugal", "raceTime": "02:52:21", "raceTimeSecs": 10341.27, "gap": "00:02:35", "gapSecs": 155.507, "dnf": false, "dns": false}, {"eventId": 1553, "eventName": "MONÇÃO e MELGAÇO GF 2025", "eventDate": "2025-09-21", "eventYear": 2025, "distance": "Mediofondo", "pos": 197, "category": "ELITES M", "gender": "M", "team": "Individual", "country": "Portugal", "raceTime": "03:29:50", "raceTimeSecs": 12590.517, "gap": "00:59:37", "gapSecs": 3577.337, "dnf": false, "dns": false}, {"eventId": 1759, "eventName": "Lousã Granfondo 2025", "eventDate": "2025-09-14", "eventYear": 2025, "distance": "Mediofondo", "pos": 90, "category": "MASTERS B", "gender": "M", "team": "Arco Cycling Team", "country": "Portugal", "raceTime": "03:13:35", "raceTimeSecs": 11615.163, "gap": "00:44:01", "gapSecs": 2641.133, "dnf": false, "dns": false}, {"eventId": 90002, "eventName": "Granfondo Agitágueda 2025", "eventDate": "2025-07-27", "eventYear": 2025, "distance": "Granfondo", "pos": 76, "category": "M Masters B", "gender": "M", "team": "Arco Cycling Team", "country": "", "raceTime": "04:57:12", "raceTimeSecs": 17832, "gap": "", "gapSecs": 0, "dnf": false, "dns": false}, {"eventId": 1388, "eventName": "Bragança Granfondo 2025", "eventDate": "2025-07-13", "eventYear": 2025, "distance": "Minifondo", "pos": 117, "category": "ELITES M", "gender": "M", "team": "Velo Clube De Bragança", "country": "Portugal", "raceTime": "02:03:13", "raceTimeSecs": 7393.22, "gap": "00:41:46", "gapSecs": 2506.053, "dnf": false, "dns": false}, {"eventId": 1692, "eventName": "GRANFONDO TERRAS DE BASTO 2025", "eventDate": "2025-06-15", "eventYear": 2025, "distance": "Granfondo", "pos": 118, "category": "MASTERS B", "gender": "M", "team": "Arco Cycling Team", "country": "Portugal", "raceTime": "05:39:36", "raceTimeSecs": 20376.247, "gap": "01:54:44", "gapSecs": 6884.367, "dnf": false, "dns": false}, {"eventId": 1681, "eventName": "Grandfondo Médio Tejo 2025", "eventDate": "2025-05-25", "eventYear": 2025, "distance": "Minifondo", "pos": 141, "category": "MASTERS A", "gender": "M", "team": "Politécnico De Tomar Bike Team", "country": "Portugal", "raceTime": "02:50:34", "raceTimeSecs": 10234.507, "gap": "00:50:15", "gapSecs": 3015.57, "dnf": false, "dns": false}, {"eventId": 1681, "eventName": "Grandfondo Médio Tejo 2025", "eventDate": "2025-05-25", "eventYear": 2025, "distance": "Minifondo", "pos": 271, "category": "MASTERS B", "gender": "M", "team": "Team Rebeldex", "country": "Portugal", "raceTime": "03:38:48", "raceTimeSecs": 13128.577, "gap": "01:38:29", "gapSecs": 5909.64, "dnf": false, "dns": false}, {"eventId": 1439, "eventName": "Love Tiles Douro Granfondo 2025", "eventDate": "2025-05-11", "eventYear": 2025, "distance": "Mediofondo", "pos": 547, "category": "MASTERS B", "gender": "M", "team": "Rc Bike", "country": "", "raceTime": "04:06:43", "raceTimeSecs": 14803.6, "gap": "01:16:16", "gapSecs": 4576.61, "dnf": false, "dns": false}, {"eventId": 1401, "eventName": "EuroBEC Granfondo 2025", "eventDate": "2025-04-06", "eventYear": 2025, "distance": "Granfondo", "pos": 104, "category": "MASTERS A", "gender": "M", "team": "Lusitano De Évora", "country": "Portugal", "raceTime": "04:01:23", "raceTimeSecs": 14483.767, "gap": "00:23:13", "gapSecs": 1393.774, "dnf": false, "dns": false}, {"eventId": 1401, "eventName": "EuroBEC Granfondo 2025", "eventDate": "2025-04-06", "eventYear": 2025, "distance": "Minifondo", "pos": 305, "category": "MASTERS E", "gender": "M", "team": "Individual", "country": "Portugal", "raceTime": "02:50:58", "raceTimeSecs": 10258.433, "gap": "01:08:17", "gapSecs": 4097.123, "dnf": false, "dns": false}, {"eventId": 1621, "eventName": "Aveiro Spring Classic 2025", "eventDate": "2025-03-23", "eventYear": 2025, "distance": "Granfondo", "pos": 312, "category": "MASTERS B", "gender": "M", "team": "Arco Cycling Team", "country": "Portugal", "raceTime": "03:16:04", "raceTimeSecs": 11764.453, "gap": "00:30:41", "gapSecs": 1841.353, "dnf": false, "dns": false}, {"eventId": 1390, "eventName": "VIANA Granfondo 2025", "eventDate": "2025-03-16", "eventYear": 2025, "distance": "Mediofondo", "pos": 121, "category": "MASTERS B", "gender": "M", "team": "Individual", "country": "Portugal", "raceTime": "02:38:22", "raceTimeSecs": 9502.607, "gap": "00:21:11", "gapSecs": 1271.544, "dnf": false, "dns": false}, {"eventId": 1590, "eventName": "GRANFONDO COIMBRA REGION 2025", "eventDate": "2025-03-02", "eventYear": 2025, "distance": "Granfondo", "pos": 216, "category": "M 35-39", "gender": "M", "team": "Lusitano De Évora", "country": "Portugal", "raceTime": "04:17:34", "raceTimeSecs": 15454.03, "gap": "00:32:29", "gapSecs": 1949.087, "dnf": false, "dns": false}, {"eventId": 1494, "eventName": "Algarve Granfondo 2025", "eventDate": "2025-02-22", "eventYear": 2025, "distance": "Mediofondo", "pos": 23, "category": "MASTERS A", "gender": "M", "team": "Mirachoro Hotels - Centro De Ciclismo De Portimão- Churrasqueira Guerreiro", "country": "Portugal", "raceTime": "02:21:44", "raceTimeSecs": 8504.69, "gap": "00:04:34", "gapSecs": 274.95, "dnf": false, "dns": false}], "canonicalTeam": "Individual"}