{"name":"Jose Feiteira","nameLower":"jose feiteira","slug":"jose-feiteira","results":[{"eventId":1390,"eventName":"VIANA Granfondo 2025","eventDate":"2025-03-16","eventYear":2025,"distance":"Mediofondo","pos":147,"category":"Masters C","gender":"M","team":"Individual","country":"Portugal","raceTime":"02:43:16","raceTimeSecs":9796.123,"gap":"00:26:05","gapSecs":1565.06,"dnf":false,"dns":false},{"eventId":90001,"eventName":"Figueira Champions Day 2025","eventDate":"2025-02-15","eventYear":2025,"distance":"Mediofondo","pos":100,"category":"Masters C","gender":"M","team":"Individual","country":"PT","raceTime":"02:19:45","raceTimeSecs":8385,"gap":"","gapSecs":0,"dnf":false,"dns":false}],"canonicalTeam":"Individual"}