{"name":"Luis Estanislau","nameLower":"luis estanislau","slug":"luis-estanislau","results":[{"eventId":1944,"eventName":"Aveiro Spring Classic 2026","eventDate":"2026-03-22","eventYear":2026,"distance":"Clássica","pos":579,"category":"Masters A","gender":"M","team":"Individual","country":"Portugal","raceTime":"03:31:15","raceTimeSecs":12675.99,"gap":"00:51:34","gapSecs":3094.323,"dnf":false,"dns":false},{"eventId":1720,"eventName":"VIANA Granfondo by KTM 2026","eventDate":"2026-03-15","eventYear":2026,"distance":"Mediofondo","pos":481,"category":"Masters A","gender":"M","team":"Individual","country":"Portugal","raceTime":"03:44:45","raceTimeSecs":13485.033,"gap":"01:09:28","gapSecs":4168.623,"dnf":false,"dns":false}],"canonicalTeam":"Individual"}