{"name":"Manuel Ferreira","nameLower":"manuel ferreira","slug":"manuel-ferreira-silva-vinha-adrap-sentir-penafiel","results":[{"eventId":1621,"eventName":"Aveiro Spring Classic 2025","eventDate":"2025-03-23","eventYear":2025,"distance":"Granfondo","pos":894,"category":"MASTERS B","gender":"M","team":"Silva & Vinha /Adrap / Sentir Penafiel","country":"Portugal","raceTime":"04:40:37","raceTimeSecs":16837.657,"gap":"01:55:14","gapSecs":6914.557,"dnf":false,"dns":false}],"canonicalTeam":"Silva & Vinha / Adrap / Sentir Penafiel"}