{"name":"MáRcio David GonçAlves MagalhãEs","nameLower":"marcio david goncalves magalhaes","slug":"marcio-david-goncalves-magalhaes-viseu-360","results":[{"eventId":90004,"eventName":"Etapa da Volta 2025","eventDate":"2025-08-12","eventYear":2025,"distance":"Etapa","pos":350,"category":"","gender":"M","team":"VISEU 360","country":"","raceTime":"03:22:52","raceTimeSecs":12172,"gap":"","gapSecs":0,"dnf":false,"dns":false},{"eventId":90004,"eventName":"Etapa da Volta 2025","eventDate":"2025-08-12","eventYear":2025,"distance":"Etapa","pos":450,"category":"","gender":"M","team":"INDIVIDUAL","country":"","raceTime":"03:28:18","raceTimeSecs":12498,"gap":"","gapSecs":0,"dnf":false,"dns":false}],"canonicalTeam":"VISEU 360"}