{"name":"Miguel Pereira","nameLower":"miguel pereira","slug":"miguel-pereira-viabike","results":[{"eventId":1720,"eventName":"VIANA Granfondo by KTM 2026","eventDate":"2026-03-15","eventYear":2026,"distance":"Minifondo","pos":216,"category":"Masters B","gender":"M","team":"Viabike","country":"Portugal","raceTime":"02:15:49","raceTimeSecs":8149.117,"gap":"00:38:31","gapSecs":2311.81,"dnf":false,"dns":false},{"eventId":1390,"eventName":"VIANA Granfondo 2025","eventDate":"2025-03-16","eventYear":2025,"distance":"Minifondo","pos":210,"category":"Masters B","gender":"M","team":"Via Bike","country":"Portugal","raceTime":"02:23:14","raceTimeSecs":8594.33,"gap":"00:43:58","gapSecs":2638.43,"dnf":false,"dns":false}],"canonicalTeam":"Viabike"}