{"name":"Ricardo Lopes","nameLower":"ricardo lopes","slug":"ricardo-lopes-bike-street-boys","results":[{"eventId":1801,"eventName":"Granfondo de Portimão 2025 ","eventDate":"2025-11-02","eventYear":2025,"distance":"Granfondo","pos":36,"category":"M ELITES","gender":"M","team":"Bike Street Boys","country":"Portugal","raceTime":"04:09:27","raceTimeSecs":14967.167,"gap":"00:32:15","gapSecs":1935.044,"dnf":false,"dns":false},{"eventId":90003,"eventName":"Granfondo 5 Quinas Sabugal 2025","eventDate":"2025-06-01","eventYear":2025,"distance":"Granfondo","pos":50,"category":"","gender":"M","team":"Bike Street Boys","country":"","raceTime":"04:24:12","raceTimeSecs":15852,"gap":"","gapSecs":0,"dnf":false,"dns":false}],"canonicalTeam":"Bike Street Boys"}