{"name":"Ricardo Santos","nameLower":"ricardo santos","slug":"ricardo-santos","results":[{"eventId":1780,"eventName":"GRANFONDO SERRA D’OSSA 2025","eventDate":"2025-10-05","eventYear":2025,"distance":"Minifondo","pos":334,"category":"MASTERS C","gender":"M","team":"Individual","country":"Portugal","raceTime":"03:05:17","raceTimeSecs":11117.6,"gap":"01:17:17","gapSecs":4637.41,"dnf":false,"dns":false},{"eventId":1612,"eventName":"TAVIRA GRANFONDO 2025","eventDate":"2025-09-28","eventYear":2025,"distance":"Granfondo","pos":73,"category":"MASTERS C","gender":"M","team":"Individual","country":"Portugal","raceTime":"04:37:53","raceTimeSecs":16673.593,"gap":"01:13:34","gapSecs":4414.27,"dnf":false,"dns":false},{"eventId":1362,"eventName":"Granfondo Serra da Estrela 2025","eventDate":"2025-06-29","eventYear":2025,"distance":"Mediofondo","pos":321,"category":"MASTERS C","gender":"M","team":"Individual","country":"Portugal","raceTime":"05:01:48","raceTimeSecs":18108.897,"gap":"02:12:44","gapSecs":7964.797,"dnf":false,"dns":false},{"eventId":1467,"eventName":"Gerês Granfondo 2025","eventDate":"2025-06-01","eventYear":2025,"distance":"Mediofondo","pos":342,"category":"MASTERS C","gender":"M","team":"Individual","country":"Portugal","raceTime":"05:24:27","raceTimeSecs":19467.88,"gap":"02:24:08","gapSecs":8648.36,"dnf":false,"dns":false},{"eventId":1681,"eventName":"Grandfondo Médio Tejo 2025","eventDate":"2025-05-25","eventYear":2025,"distance":"Mediofondo","pos":261,"category":"MASTERS A","gender":"M","team":"Individual","country":"Portugal","raceTime":"04:03:37","raceTimeSecs":14617.367,"gap":"01:11:25","gapSecs":4285.85,"dnf":false,"dns":false},{"eventId":1656,"eventName":"Granfondo Torres Vedras 2025","eventDate":"2025-04-27","eventYear":2025,"distance":"Granfondo","pos":180,"category":"MASTERS B","gender":"M","team":"Individual","country":"Portugal","raceTime":"05:57:21","raceTimeSecs":21441.22,"gap":"02:10:18","gapSecs":7818.663,"dnf":false,"dns":false},{"eventId":1401,"eventName":"EuroBEC Granfondo 2025","eventDate":"2025-04-06","eventYear":2025,"distance":"Mediofondo","pos":645,"category":"MASTERS C","gender":"M","team":"Individual","country":"Portugal","raceTime":"04:01:54","raceTimeSecs":14514.267,"gap":"01:33:13","gapSecs":5593.12,"dnf":false,"dns":false}]}